HISTORY.txt
MANIFEST.in
bootstrap.py
buildout.cfg
setup.py
redturtle/__init__.py
redturtle.entiterritoriali.egg-info/PKG-INFO
redturtle.entiterritoriali.egg-info/SOURCES.txt
redturtle.entiterritoriali.egg-info/dependency_links.txt
redturtle.entiterritoriali.egg-info/entry_points.txt
redturtle.entiterritoriali.egg-info/namespace_packages.txt
redturtle.entiterritoriali.egg-info/not-zip-safe
redturtle.entiterritoriali.egg-info/requires.txt
redturtle.entiterritoriali.egg-info/top_level.txt
redturtle/entiterritoriali/EntiCriteria.py
redturtle/entiterritoriali/README.rst
redturtle/entiterritoriali/__init__.py
redturtle/entiterritoriali/config.py
redturtle/entiterritoriali/configure.zcml
redturtle/entiterritoriali/profiles/default/metadata.xml
redturtle/entiterritoriali/profiles/default/types.xml
redturtle/entiterritoriali/profiles/default/types/EntiCriteria.xml
redturtle/entiterritoriali/tests/__init__.py
redturtle/entiterritoriali/tests/test_doctest.py
redturtle/entiterritoriali/vocabulary/__init__.py
redturtle/entiterritoriali/vocabulary/sqlite3.db