Metadata-Version: 1.1
Name: redturtle.entiterritoriali
Version: 0.4.0
Summary: Package contatins all italian enti territoriali in sqlite db
Home-page: http://plone.org/products/redturtle.entiterritoriali
Author: RedTurtle Technology
Author-email: sviluppoplone@redturtle.net
License: GPL
Platform: UNKNOWN
Classifier: Programming Language :: Python
Classifier: Framework :: Plone
Classifier: Development Status :: 5 - Production/Stable
Classifier: Topic :: Software Development :: Libraries :: Python Modules
